{
  "Ads": [
    {
      "select_main_ads": "ADMOB",
      "select_backup_ads":"APPLOVIN-M",
      "main_ads_banner": "ca-app-pub-1065675718452781/1887340271",
      "main_ads_intertitial":"ca-app-pub-1065675718452781/9703069359",
      "main_ads_natives":"ca-app-pub-1065675718452781/8168843449",
      "main_ads_rewards":"null",
      "backup_ads_natives":"null",
      "backup_ads_banner":"06db6056a049cddf",
      "backup_ads_intertitial":"531edd0e79ace0cf",
      "backup_ads_rewards":"null",
      "open_ads_admob":"null",
      "open_ads_alien":"null",
      "switch_open_ads":"1",
      "switch_banner_natives_ads":"1",
      "interval_intertitial": 5,
      "initialize_sdk":"null",
      "initialize_sdk_backup_ads":"null",
      "high_paying_keyword_1": "null",
      "high_paying_keyword_2": "null",
      "high_paying_keyword_3": "null",
      "high_paying_keyword_4": "null",
      "high_paying_keyword_5": "null",
      "status_app": "0",
      "link_redirect": "https://",
      "on_off_category":"2"
    }
  ],
  "More":
  [
    {
      "id":1,
      "title":"Mommy Long Legs Wallpapers",
      "image":"https://play-lh.googleusercontent.com/Sas0iSgX5cgnfiPDPJ509Uo964bXg9ABEcbc8Ynqruq8IYH0G3W0dIt_f5WKchvmuOng=w240-h480-rw",
      "link":"https://play.google.com/store/apps/details?id=com.RubahMerah.MommyLongLegsWallpapers&hl=id&gl=US"
    },
	{
      "id":2,
      "title":"Optimus Prime Wallpaper",
      "image":"https://play-lh.googleusercontent.com/nYwlZGdvgUReG7Du2bEwg6BFqHqLCG49N597hsIEKxHui0Atbern8vMmA-p85NDHiwGi=w240-h480-rw",
      "link":"https://play.google.com/store/apps/details?id=com.RubahMerah.OptimusPrimeWallpaper&hl=id&gl=US"
    },
	{
      "id":3,
      "title":"Clover Anime Wallpaper HD",
      "image":"https://play-lh.googleusercontent.com/SyZuueFT6_CA6emJLSYzZ6z6AG-8yGeQ_Jniv2ES2nFPq13MX5Ylngb0VuZWotLgm_4=w240-h480-rw",
      "link":"https://play.google.com/store/apps/details?id=com.RubahMerah.BlackCloverWallpaper&hl=id&gl=US"
    },
	{
      "id":4,
      "title":"Channa Fish Wallpaper",
      "image":"https://play-lh.googleusercontent.com/PZ8KhooRTWkeElf3_moEM7XmU3sE125bin-nV-2G6tPvvevbM0jAmBQxqmJBLpGkArk=w240-h480-rw",
      "link":"https://play.google.com/store/apps/details?id=com.RubahMerah.ChannaFishWallpaper&hl=id&gl=US"
    },
	{
      "id":5,
      "title":"FFF Fire Wallpaper",
      "image":"https://play-lh.googleusercontent.com/03FPy41yGdU7f5qSIS6mQQAyoPwuK6wwfQcHivWAQHoH9gd0VXlK8zHFX4KP3hKnKAY=w240-h480-rw",
      "link":"https://play.google.com/store/apps/details?id=com.RubahMerah.FFFFireWallpaper&hl=id&gl=US"
    },
	{
      "id":6,
      "title":"Pony Wallpapers HD",
      "image":"https://play-lh.googleusercontent.com/lm5sUnw3376K3IbHzM7MoYPmuKOaWAj8jWlS6PHviuXnb9mHdJKHm-X0-e_xBR7g4yY=w240-h480-rw",
      "link":"https://play.google.com/store/apps/details?id=com.RubahMerah.PonyWallpapersHD&hl=id&gl=US"
    },
	{
      "id":7,
      "title":"Sanrio Wallpaper",
      "image":"https://play-lh.googleusercontent.com/FqoCzRIJu_qBBfqfXijIj9OknmMni8uqrr4P1YCy8dhG2UONcAttHyNnkz06htx3BLU=w240-h480-rw",
      "link":"https://play.google.com/store/apps/details?id=com.RubahMerah.SanrioWallpaper&hl=id&gl=US"
    },
	{
      "id":8,
      "title":"Predator Wallpaper 4K",
      "image":"https://play-lh.googleusercontent.com/hsL5o06mdgmZLIrngxk06k8IobZHktVwleQ-YRXbDKlvC9FbRz_iQk-aggCWVKpN6qAp=w240-h480-rw",
      "link":"https://play.google.com/store/apps/details?id=com.RubahMerah.PredatorWallpaper4K&hl=id&gl=US"
    },
	{
      "id":9,
      "title":"Way of Water Ava Wallpapers",
      "image":"https://play-lh.googleusercontent.com/u0xrQ1JgpsM4cMFaLkvQRNKOuoVSDM54Rd63rsWUqZouHcioPp1zGin0iiZMHkVw2iA=w240-h480-rw",
      "link":"https://play.google.com/store/apps/details?id=com.RubahMerah.Avatar2Wallpaper&hl=id&gl=US"
    },
	{
      "id":10,
      "title":"Horror Wallpaper",
      "image":"https://play-lh.googleusercontent.com/wHS-NfZ-gDbrNXzk7W91lfjo243SkBuB-QQhlkxaCDJ672SJ4aBqoYQ974KSXuJIz60=w240-h480-rw",
      "link":"https://play.google.com/store/apps/details?id=com.RubahMerah.HorrorWallpaper&hl=id&gl=US"
    },
	{
      "id":11,
      "title":"Kuromi Wallpaper",
      "image":"https://play-lh.googleusercontent.com/xgG2EE5HqnEMe5MqvsM_XV5zpmtPWbBkaq85f3YV43J_YeDPdtUtgzZjFPQFqa-CV9s=w240-h480-rw",
      "link":"https://play.google.com/store/apps/details?id=com.RubahMerah.KuromiWallpaper&hl=id&gl=US"
    },
	{
      "id":12,
      "title":"Superheroes Wallpaper",
      "image":"https://play-lh.googleusercontent.com/ahI7U14ngPwEbSNE9WYIWJxGjMpP3xnrIAdsC3UzSKbNCamMIVBtL2k5vq64kR3QLrA=w240-h480-rw",
      "link":"https://play.google.com/store/apps/details?id=com.RubahMerah.SuperheroesWallpaper&hl=id&gl=US"
    },
	{
      "id":13,
      "title":"Demon Slayer Wallpaper Kimetsu",
      "image":"https://play-lh.googleusercontent.com/aBbkSPfeDap3qLN_EBjOBavn699P9AKlsLVDHcqp8ryZQ5M-jlpdT7gJ1kNaqFGGKdxV=w240-h480-rw",
      "link":"https://play.google.com/store/apps/details?id=com.RubahMerah.DemonSlayerWallpaperKimetsu&hl=id&gl=US"
    },
	{
      "id":14,
      "title":"Spy x Family Wallpaper",
      "image":"https://play-lh.googleusercontent.com/Ieo9z3KSIhm2cz46J50eLhpYLgn68U23mK5ear61TcsQ_yTQgOsUSmtDrG1TNL64fX8=w240-h480-rw",
      "link":"https://play.google.com/store/apps/details?id=com.RubahMerah.SpyxFamilyWallpaper&hl=id&gl=US"
    },
	{
      "id":15,
      "title":"Gaming Wallpaper",
      "image":"https://play-lh.googleusercontent.com/95fvkVcq9kubqKrCiBrASfokfF-lyMIK10NfKv1DztM4omIbxZb1UTBBTPgJOWxwu-w=w240-h480-rw",
      "link":"https://play.google.com/store/apps/details?id=com.RubahMerah.GamingWallpaper&hl=id&gl=US"
    },
	{
      "id":16,
      "title":"Kaiju Godzilla Wallpaper",
      "image":"https://play-lh.googleusercontent.com/f-O7yohtloQUZPIKcqnRkYLQ4y7kZvpIsmh9KNOiq04HpOFijubr0BCTfc1yR50dfW6i=w240-h480-rw",
      "link":"https://play.google.com/store/apps/details?id=com.RubahMerah.KaijuGodzillaWallpaper&hl=id&gl=US"
    },
	{
      "id":17,
      "title":"Venom Wallpaper",
      "image":"https://play-lh.googleusercontent.com/TnZjl8bSKNoe8qRZDUjh3QqdON1neJCzLN5KE-sip_oHt-TQnp4RotQ-CVoLBg4-hyNS=w240-h480-rw",
      "link":"https://play.google.com/store/apps/details?id=com.RubahMerah.VenomWallpaper&hl=id&gl=US"
    },
	{
      "id":18,
      "title":"NFL Football Wallpaper",
      "image":"https://play-lh.googleusercontent.com/skk5cqD4aSPgTz6VXAP4DwjMZImk6KsjcMQiMtmt6HOsxmPNBjzQIBdIdzAEDx3xzA=w240-h480-rw",
      "link":"https://play.google.com/store/apps/details?id=com.RubahMerah.NFLFootballWallpaper&hl=id&gl=US"
    },
	{
      "id":19,
      "title":"My Genshin Wallpaper",
      "image":"https://play-lh.googleusercontent.com/aqFQoF_r3qXRtnKIUQrhTfpxmpU_A7rpczmUMoANi7jZNkpvvdoBNkJy_NcWtXnJKwUh=w240-h480-rw",
      "link":"https://play.google.com/store/apps/details?id=com.RubahMerah.MyGenshinWallpaper&hl=id&gl=US"
    },
	{
      "id":20,
      "title":"Chainsaw Man Wallpaper",
      "image":"https://play-lh.googleusercontent.com/h_88wMXeiApW7Kp1RbUJsJ8hclXix8Mw8EVef8d1nBFD-mnEvoi8M9Yn6Hh-Um-7gPvA=w240-h480-rw",
      "link":"https://play.google.com/store/apps/details?id=com.RubahMerah.ChainsawManWallpaper&hl=id&gl=US"
    },
	{
      "id":21,
      "title":"Cute Cat Wallpapers",
      "image":"https://play-lh.googleusercontent.com/OjA_Nmv8IrJNdJBFx57w_fxclKiLllnukwrvLd8RFClUoNnD3MSY2YNFe6RwkXdxQw=w240-h480-rw",
      "link":"https://play.google.com/store/apps/details?id=com.RubahMerah.CuteCatWallpapers&hl=id&gl=US"
    },
	{
      "id":22,
      "title":"Moon Knight Wallpaper",
      "image":"https://play-lh.googleusercontent.com/b0baZegC0G1T2SQ8MXA5gxm5PRExqwnqJojXmtYn8gqGh21V-6FBnPJz6vT7_2Amjg=w240-h480-rw",
      "link":"https://play.google.com/store/apps/details?id=com.RubahMerah.MoonKnightWallpaper&hl=id&gl=US"
    },
	{
      "id":23,
      "title":"Sports Car Wallpaper HD",
      "image":"https://play-lh.googleusercontent.com/iJL1EVIVAjoObxhbfmzGtOYFFCLAlAV-eG4ue4XftqSZutvk7htRtkGLx1GxKoM2hxg=w240-h480-rw",
      "link":"https://play.google.com/store/apps/details?id=com.RubahMerah.LamborghiniWallpaperHD&hl=id&gl=US"
    },
	{
      "id":24,
      "title":"Gacha Wallpaper",
      "image":"https://play-lh.googleusercontent.com/vI0r7P0XaHNfFZxYFf1Ga0dcZudVR3WcX-gY64nIXpTcwnDlKh8cxqz-QBbWbdQ8EzF0=w240-h480-rw",
      "link":"https://play.google.com/store/apps/details?id=com.RubahMerah.GachaWallpaper&hl=id&gl=US"
    },
	{
      "id":25,
      "title":"Football Wallpaper HD",
      "image":"https://play-lh.googleusercontent.com/a11kqMVKqubyCWJ0M52KCra0XCGOrCkydi88mQB-LfU_94A3BGx4JH2yBotxcblVO3AK=w240-h480-rw",
      "link":"https://play.google.com/store/apps/details?id=com.RubahMerah.FootballWallpaperHD&hl=id&gl=US"
    },
	{
      "id":26,
      "title":"Neon Mask Wallpaper",
      "image":"https://play-lh.googleusercontent.com/wcMdcCyKOl3pD2LMSvWX3HmOgt49pjW9Cv1n33U03jZlOVmoogg2hbbfHKKbOnH5jUs=w240-h480-rw",
      "link":"https://play.google.com/store/apps/details?id=com.RubahMerah.NeonMaskWallpaper&hl=id&gl=US"
    },
	{
      "id":27,
      "title":"Shinobu Kochou Wallpapers",
      "image":"https://play-lh.googleusercontent.com/ilKa1AEmjhSrXOYZnOHbTWGIt6A_agmxo2Nt-OdlxwaH1VPpsMt86obItKT7MxM-P4A-=w240-h480-rw",
      "link":"https://play.google.com/store/apps/details?id=com.RubahMerah.ShinobuKochouWallpapers&hl=id&gl=US"
    },
	{
      "id":28,
      "title":"Anime Wallpaper HD",
      "image":"https://play-lh.googleusercontent.com/01hmE2anUIJ6uS7rJkWSbCMud4wTe88Bwpy6ahqKk5ioYdQskebn6RhDFXHlsPCKI2I=w240-h480-rw",
      "link":"https://play.google.com/store/apps/details?id=com.RubahMerah.AnimeWallpaperHD&hl=id&gl=US"
    },
	{
      "id":29,
      "title":"The Owl House Wallpapers",
      "image":"https://play-lh.googleusercontent.com/Qj64TB4tWp82hC_r-o-xLdyvt27CgyDLwzfu5yWKRoQo98laGd7jOLfNwnPhhIjVH7I=w240-h480-rw",
      "link":"https://play.google.com/store/apps/details?id=com.RubahMerah.TheOwlHouseWallpapers&hl=id&gl=US"
    },
	{
      "id":30,
      "title":"Unicorn Wallpaper HD",
      "image":"https://play-lh.googleusercontent.com/bQz9Mb1I-h6L-K82mHSkaaKVPM5IoIYmD6CctfzcN1iZwSPvZ9bpssjMFCVANJMdxze5=w240-h480-rw",
      "link":"https://play.google.com/store/apps/details?id=com.RubahMerah.UnicornWallpaperHD&hl=id&gl=US"
    },
	{
      "id":31,
      "title":"Huggy Wuggy Wallpaper HD",
      "image":"https://play-lh.googleusercontent.com/dHAqkbSwWWeZjg9UqLP3mxgzZ7CrROTtJi1kolVzUq1FYXJCUXPdftdR_yqdpwowaOg6=w240-h480-rw",
      "link":"https://play.google.com/store/apps/details?id=com.RubahMerah.HuggyWuggyWallpaperHD&hl=id&gl=US"
    },
	{
      "id":32,
      "title":"Wednesday Addams Wallpaper",
      "image":"https://play-lh.googleusercontent.com/5JcgGAWgeL6_PDBAR62Dnn4vQO6LPMLvOflG_LndS7KyYpCPxB6VvfMX1VnwKpgqfLw=w240-h480-rw",
      "link":"https://play.google.com/store/apps/details?id=com.RubahMerah.WednesdayAddamsWallpaper&hl=id&gl=US"
    },
	{
      "id":33,
      "title":"Shining Nikki Wallpaper",
      "image":"https://play-lh.googleusercontent.com/-RN2LW9IIpAe1YUq4BWn3M-foR87krY9hTWiwQ1PkEYbkgYKkbyUjonT8Y4QkQSXZ9c=w240-h480-rw",
      "link":"https://play.google.com/store/apps/details?id=com.RubahMerah.ShiningNikkiWallpaper&hl=id&gl=US"
    },
	{
      "id":34,
      "title":"Galaxy Wolf Wallpaper",
      "image":"https://play-lh.googleusercontent.com/pkZfMGaDqVf53U9EPXRIDxtidEOpT8AiJ1snaCvFuP0ZFff2jV2NOCFD2cD3h3Mzt-n0=w240-h480-rw",
      "link":"https://play.google.com/store/apps/details?id=com.RubahMerah.GalaxyWolfWallpaper&hl=id&gl=US"
    },
	{
      "id":35,
      "title":"Pk Xd Wallpaper",
      "image":"https://play-lh.googleusercontent.com/ucwtj9cV-IJjJ9emBfpg6gmjHizplqug4r25bBTAuOtoChuHs0iIKL-E3AsiWsrykw=w240-h480-rw",
      "link":"https://play.google.com/store/apps/details?id=com.RubahMerah.PKXDWallpaper&hl=id&gl=US"
    },
	{
      "id":36,
      "title":"Battle Royale Wallpaper HD",
      "image":"https://play-lh.googleusercontent.com/vybcj57iCzxjr1m7G6e2nJn4bpxRZsxMJtjNC54DCA6qjYcfhmqAH14VWGJ_UqS9nN0=w240-h480-rw",
      "link":"https://play.google.com/store/apps/details?id=com.RubahMerah.BattleRoyaleWallpaperHD&hl=id&gl=US"
    },
	{
      "id":37,
      "title":"Cartoon Wallpaper HD",
      "image":"https://play-lh.googleusercontent.com/YbULB6htT5ZjDzGNwrnykFBj-84bxH94xiIQIcd8CiCvYddB6npAl-ufMkDx_Ae9UMk=w240-h480-rw",
      "link":"https://play.google.com/store/apps/details?id=com.RubahMerah.CartoonWallpaperHD&hl=id&gl=US"
    },
	{
      "id":38,
      "title":"Sakura School Wallpaper",
      "image":"https://play-lh.googleusercontent.com/9ATVE6VAHs8msU4ClNqbWQko-c7a5Y9s8sO3mN5wZgAslt9z7onBTIyzHw7bgjEerQ=w240-h480-rw",
      "link":"https://play.google.com/store/apps/details?id=com.RubahMerah.SakuraSchoolWallpaper&hl=id&gl=US"
    },
	{
      "id":39,
      "title":"Cute Bear Cartoon Wallpaper",
      "image":"https://play-lh.googleusercontent.com/2H-k8zQ-jZCjgRIo5qNFPgIOGFumqR3WnCZ3MhtSxvzSGARVLaxjF5wnxtNy6fHrUlt4=w240-h480-rw",
      "link":"https://play.google.com/store/apps/details?id=com.RubahMerah.CuteBearCartoonWallpaper&hl=id&gl=US"
    },
	{
      "id":40,
      "title":"Wallpaper 4K UHD",
      "image":"https://play-lh.googleusercontent.com/L8rO3TRcrQ4VNKEwWN9huMFOuYiIDpUkINYdoxyrn7q1x5I6m35muVq2mDEG_zrhsK8=w240-h480-rw",
      "link":"https://play.google.com/store/apps/details?id=com.RubahMerah.Wallpaper4KUHD&hl=id&gl=US"
    },
	{
      "id":41,
      "title":"Car Wallpaper HD",
      "image":"https://play-lh.googleusercontent.com/JgI9Arfd-bn_IkiPjrvBhldX-UiF5xkuPO0JqPowW62AqbZK8DDTSw8NeygZu-LL7A=w240-h480-rw",
      "link":"https://play.google.com/store/apps/details?id=com.RubahMerah.CarWallpaperHD&hl=id&gl=US"
    },
	{
      "id":42,
      "title":"Anime Kimono Wallpaper",
      "image":"https://play-lh.googleusercontent.com/lQWJEpb0dGRCmqR008QR2OjaRwU9CdEEoZVKhmGgv7IKMbWf6-kRwPRXC3wJ1Px0a2Zl=w240-h480-rw",
      "link":"https://play.google.com/store/apps/details?id=com.RubahMerah.AnimeKimonoWallpaper&hl=id&gl=US"
    },
	{
      "id":43,
      "title":"Flower Wallpaper HD",
      "image":"https://play-lh.googleusercontent.com/WDdBaCmGddWKFjA8aOgvmPdUoTEYBmBMacZvldpBgj5io7vVL3VTHxHJ6wx9BOGD=w240-h480-rw",
      "link":"https://play.google.com/store/apps/details?id=com.RubahMerah.FlowerWallpaperHD&hl=id&gl=US"
    },
	{
      "id":44,
      "title":"Rainbow Friend Wallpaper",
      "image":"https://play-lh.googleusercontent.com/89CJD0h5NocBCdU_p29nQdA0Oi8ggASCJpnen4ck5S4OeX2pBQr0-ifKLRlaOmnGxJw=w240-h480-rw",
      "link":"https://play.google.com/store/apps/details?id=com.RubahMerah.RainbowFriendWallpaper&hl=id&gl=US"
    },
	{
      "id":45,
      "title":"Doll Wallpaper HD",
      "image":"https://play-lh.googleusercontent.com/0xNrRtSUEAE_7U6tIZG8VHFdt1Q7VH10I0k_r-5meynHmZBOS4wp8EzwdbaanAzm4fqQ=w240-h480-rw",
      "link":"https://play.google.com/store/apps/details?id=com.RubahMerah.DollWallpaperHD&hl=id&gl=US"
    },
	{
      "id":46,
      "title":"Roman Reigns Wallpaper",
      "image":"https://play-lh.googleusercontent.com/_LHx4t0V4XKslzU5qDDuAxaq4VPwjTWluBliyv4FN6kcSBmR0knucgjRgOnaQNVvIQ=w240-h480-rw",
      "link":"https://play.google.com/store/apps/details?id=com.RubahMerah.RomanReignsWallpaper&hl=id&gl=US"
    },
	{
      "id":47,
      "title":"Death Wolf Wallpaper",
      "image":"https://play-lh.googleusercontent.com/XooxUne237Er64t5-frBdqwJJ60XcNuBpp3vZUKkbYZ7GaZV1JBvwFJY1sZVQ4POCQ=w240-h480-rw",
      "link":"https://play.google.com/store/apps/details?id=com.RubahMerah.DeathWolfWallpaper&hl=id&gl=US"
    },
	{
      "id":48,
      "title":"Kawasaki Ninja Wallpaper",
      "image":"https://play-lh.googleusercontent.com/bkiOr9AQlekSKriLwYO0WBVW-r_HnCsq_eLmrn07a3hSLLSrxHWzrmFmGOFbcEuA5g=w240-h480-rw",
      "link":"https://play.google.com/store/apps/details?id=com.RubahMerah.KawasakiNinjaWallpaper&hl=id&gl=US"
    },
	{
      "id":49,
      "title":"Yamaha MT15 Wallpaper",
      "image":"https://play-lh.googleusercontent.com/QDm3AMPICHtRKqtr-4OVoZJd6CSxGrV1zdXBdtJ2ArmimwI6s3eZCnOhGXwgsyyxT0A=w240-h480-rw",
      "link":"https://play.google.com/store/apps/details?id=com.RubahMerah.YamahaMT15Wallpaper&hl=id&gl=US"
    }
	
  ],

  "Categories": 
  [
    {
      "id": 1,
      "name_category": "All Image",
      "image": "https://i.pinimg.com/564x/6a/9a/61/6a9a61ad566661ca325e5a8a591ef722.jpg"

    }
  ],

  "Data":
  [
    {
      "id":1,
      "name_category": "All Image",
      "title":"1",
      "image":"https://i.pinimg.com/564x/65/99/19/659919f6c92f42697c7f85932bfa9c41.jpg"
    },
	{
      "id":2,
      "name_category": "All Image",
      "title":"2",
      "image":"https://i.pinimg.com/564x/8c/b5/c9/8cb5c963dfb9b110bf79bfc518ad3abc.jpg"
    },
	{
      "id":3,
      "name_category": "All Image",
      "title":"3",
      "image":"https://i.pinimg.com/564x/fe/59/7a/fe597a58f22acdfa3b1ed9f6ea24f2a2.jpg"
    },
	{
      "id":4,
      "name_category": "All Image",
      "title":"4",
      "image":"https://i.pinimg.com/564x/6a/9a/61/6a9a61ad566661ca325e5a8a591ef722.jpg"
    },
	{
      "id":5,
      "name_category": "All Image",
      "title":"5",
      "image":"https://i.pinimg.com/564x/ed/6d/58/ed6d587840b104d6c490fcf09b4b1a51.jpg"
    },
	{
      "id":6,
      "name_category": "All Image",
      "title":"6",
      "image":"https://i.pinimg.com/564x/06/e5/e9/06e5e9a881fbbc156cdb4cad403a32a6.jpg"
    },
	{
      "id":7,
      "name_category": "All Image",
      "title":"7",
      "image":"https://i.pinimg.com/564x/10/e1/2d/10e12d365aab4ba7fae8db951c0f02e4.jpg"
    },
	{
      "id":8,
      "name_category": "All Image",
      "title":"8",
      "image":"https://i.pinimg.com/736x/33/85/9f/33859fae413a91508f8301769c7faeec.jpg"
    },
	{
      "id":9,
      "name_category": "All Image",
      "title":"9",
      "image":"https://i.pinimg.com/564x/72/c7/35/72c735232d68cd8c4c87b046fb7d6497.jpg"
    },
	{
      "id":10,
      "name_category": "All Image",
      "title":"10",
      "image":"https://i.pinimg.com/564x/f1/1f/25/f11f25533626fbf554757ed47be313b1.jpg"
    },
	{
      "id":11,
      "name_category": "All Image",
      "title":"11",
      "image":"https://i.pinimg.com/564x/a5/af/60/a5af604530a43bd1021fcb1fdb412dd5.jpg"
    },
	{
      "id":12,
      "name_category": "All Image",
      "title":"12",
      "image":"https://i.pinimg.com/564x/c3/58/31/c3583107d0589603d34da129b0f46ba2.jpg"
    },
	{
      "id":13,
      "name_category": "All Image",
      "title":"13",
      "image":"https://i.pinimg.com/564x/b0/0c/b2/b00cb2afa26c22ff5833e7d4e364b4af.jpg"
    },
	{
      "id":14,
      "name_category": "All Image",
      "title":"14",
      "image":"https://i.pinimg.com/750x/83/87/8d/83878d5629a2a3ee3b5dc1fea2642c46.jpg"
    },
	{
      "id":15,
      "name_category": "All Image",
      "title":"15",
      "image":"https://i.pinimg.com/750x/ac/ed/ec/acedec71bc1fca6db29cd81be33f9aa0.jpg"
    },
	{
      "id":16,
      "name_category": "All Image",
      "title":"16",
      "image":"https://i.pinimg.com/564x/fd/1f/28/fd1f28cc2e711b130bcbc89d3f9fb853.jpg"
    },
	{
      "id":17,
      "name_category": "All Image",
      "title":"17",
      "image":"https://i.pinimg.com/564x/54/64/fe/5464fe6e402b07b4f504030c87db07e1.jpg"
    },
	{
      "id":18,
      "name_category": "All Image",
      "title":"18",
      "image":"https://i.pinimg.com/564x/98/dd/5c/98dd5c97a8f214f49b5a4f6a77736c08.jpg"
    },
	{
      "id":19,
      "name_category": "All Image",
      "title":"19",
      "image":"https://i.pinimg.com/564x/e7/4f/77/e74f7718be4aa85efb5dc131ee21f486.jpg"
    },
	{
      "id":20,
      "name_category": "All Image",
      "title":"20",
      "image":"https://i.pinimg.com/564x/dd/b7/0f/ddb70fb3652af8ef6ed20e7c9ecdc0f5.jpg"
    },
	{
      "id":21,
      "name_category": "All Image",
      "title":"21",
      "image":"https://i.pinimg.com/564x/d0/41/ee/d041ee6390bc7121d280a6161e0a60d8.jpg"
    },
	{
      "id":22,
      "name_category": "All Image",
      "title":"22",
      "image":"https://i.pinimg.com/564x/b2/9d/37/b29d3792fbaef289b457fb19e03f6b0a.jpg"
    },
	{
      "id":23,
      "name_category": "All Image",
      "title":"23",
      "image":"https://i.pinimg.com/564x/c8/c0/4c/c8c04c953d1563e0c45412544bcee540.jpg"
    },
	{
      "id":24,
      "name_category": "All Image",
      "title":"24",
      "image":"https://i.pinimg.com/564x/be/7c/2a/be7c2aa2eaa4ec761eeb2470ee91ec4c.jpg"
    },
	{
      "id":25,
      "name_category": "All Image",
      "title":"25",
      "image":"https://i.pinimg.com/564x/43/26/42/43264205daf18b173864e65fd6a4f733.jpg"
    },
	{
      "id":26,
      "name_category": "All Image",
      "title":"26",
      "image":"https://i.pinimg.com/564x/a5/cd/2a/a5cd2af8b8f50adb2000c3ad114a00f0.jpg"
    },
	{
      "id":27,
      "name_category": "All Image",
      "title":"27",
      "image":"https://i.pinimg.com/564x/4d/0c/5a/4d0c5a5537c5b75a2c7df9c5bec63378.jpg"
    },
	{
      "id":28,
      "name_category": "All Image",
      "title":"28",
      "image":"https://i.pinimg.com/564x/54/4c/10/544c1038185fd6730824b0ceca1ab7d8.jpg"
    },
	{
      "id":29,
      "name_category": "All Image",
      "title":"29",
      "image":"https://i.pinimg.com/564x/0f/da/79/0fda7916b3f1c5b41ce849dbfeefa3e9.jpg"
    },
	{
      "id":30,
      "name_category": "All Image",
      "title":"30",
      "image":"https://i.pinimg.com/564x/eb/c9/87/ebc98729670859f4e4b47c37dbaf43d6.jpg"
    },
	{
      "id":31,
      "name_category": "All Image",
      "title":"31",
      "image":"https://i.pinimg.com/736x/8f/c6/a0/8fc6a0698c2823ccd9b1e11ab8eecff4.jpg"
    },
	{
      "id":32,
      "name_category": "All Image",
      "title":"32",
      "image":"https://i.pinimg.com/564x/91/63/c3/9163c381004016ed0f4910e1b3f4bdab.jpg"
    },
	{
      "id":33,
      "name_category": "All Image",
      "title":"33",
      "image":"https://i.pinimg.com/564x/59/cd/14/59cd14d205249bbaf94b26df4951be3a.jpg"
    },
	{
      "id":34,
      "name_category": "All Image",
      "title":"34",
      "image":"https://i.pinimg.com/564x/91/ee/41/91ee4198fd460b196856fe51219eeb10.jpg"
    },
	{
      "id":35,
      "name_category": "All Image",
      "title":"35",
      "image":"https://i.pinimg.com/564x/d5/97/eb/d597ebd9139ed0864b638ccc98fce881.jpg"
    },
	{
      "id":36,
      "name_category": "All Image",
      "title":"36",
      "image":"https://i.pinimg.com/564x/6c/78/98/6c7898cfcd6e02bfb5bf5b8a901f5a77.jpg"
    },
	{
      "id":37,
      "name_category": "All Image",
      "title":"37",
      "image":"https://i.pinimg.com/564x/3b/9c/17/3b9c178d043ec4e4a99fa8080b6d3238.jpg"
    },
	{
      "id":38,
      "name_category": "All Image",
      "title":"38",
      "image":"https://i.pinimg.com/564x/93/28/cc/9328cca1694a20204c135f1a7240ee0b.jpg"
    },
	{
      "id":39,
      "name_category": "All Image",
      "title":"39",
      "image":"https://i.pinimg.com/564x/34/5c/40/345c4059125a8d4837208979fadc1828.jpg"
    },
	{
      "id":40,
      "name_category": "All Image",
      "title":"40",
      "image":"https://i.pinimg.com/564x/7b/15/d9/7b15d9442bda05d399d967c8114027bf.jpg"
    },
	{
      "id":41,
      "name_category": "All Image",
      "title":"41",
      "image":"https://i.pinimg.com/564x/6d/7c/a9/6d7ca945c5bd9888155fc8557dd9fc63.jpg"
    },
	{
      "id":42,
      "name_category": "All Image",
      "title":"42",
      "image":"https://i.pinimg.com/564x/1e/aa/fb/1eaafb9330ae778e1fe7580523931178.jpg"
    },
	{
      "id":43,
      "name_category": "All Image",
      "title":"43",
      "image":"https://i.pinimg.com/564x/eb/c3/51/ebc3514e63ee38513447e69a326a1667.jpg"
    },
	{
      "id":44,
      "name_category": "All Image",
      "title":"44",
      "image":"https://i.pinimg.com/564x/93/e2/bb/93e2bb11741c340c82dbe9bcff35dc22.jpg"
    },
	{
      "id":45,
      "name_category": "All Image",
      "title":"45",
      "image":"https://i.pinimg.com/564x/5b/db/08/5bdb0899d65c53a6c1d7ddb0c2524955.jpg"
    },
	{
      "id":46,
      "name_category": "All Image",
      "title":"46",
      "image":"https://i.pinimg.com/564x/1a/78/b7/1a78b72072a4807e9fde156d895b7613.jpg"
    },
	{
      "id":47,
      "name_category": "All Image",
      "title":"47",
      "image":"https://i.pinimg.com/564x/62/f0/2a/62f02af017113b8f79e387e69728b2dc.jpg"
    },
	{
      "id":48,
      "name_category": "All Image",
      "title":"48",
      "image":"https://i.pinimg.com/564x/d2/07/0d/d2070de43d8aa3e51a63fbce0713d496.jpg"
    },
	{
      "id":49,
      "name_category": "All Image",
      "title":"49",
      "image":"https://i.pinimg.com/564x/11/83/98/11839873cade2db1f219df39f244e38f.jpg"
    },
	{
      "id":50,
      "name_category": "All Image",
      "title":"50",
      "image":"https://i.pinimg.com/564x/8c/53/ff/8c53ff4a1926f51555f33211adb0b46e.jpg"
    },
	{
      "id":51,
      "name_category": "All Image",
      "title":"51",
      "image":"https://i.pinimg.com/564x/56/6f/bc/566fbcc6d1f6854bdd3f1f437b80be43.jpg"
    },
	{
      "id":52,
      "name_category": "All Image",
      "title":"52",
      "image":"https://i.pinimg.com/564x/ff/8a/aa/ff8aaa3b4d2ee030557c724df4e69f3e.jpg"
    },
	{
      "id":53,
      "name_category": "All Image",
      "title":"53",
      "image":"https://i.pinimg.com/564x/13/dc/a2/13dca2b1c0c05fd301f9c100152ea54e.jpg"
    },
	{
      "id":54,
      "name_category": "All Image",
      "title":"54",
      "image":"https://i.pinimg.com/564x/d4/15/a6/d415a65ee9a30c564f73ac19a63e5375.jpg"
    },
	{
      "id":55,
      "name_category": "All Image",
      "title":"55",
      "image":"https://i.pinimg.com/564x/05/8a/1a/058a1aaad82d513df2330ac1e71fba0a.jpg"
    }
    
  ]
}
